ZeroXRequests/RawRequests.py
ZeroXRequests/RequestUtils.py
ZeroXRequests/__init__.py
ZeroXRequests-1.1.dist-info/METADATA
ZeroXRequests-1.1.dist-info/WHEEL
ZeroXRequests-1.1.dist-info/top_level.txt
ZeroXRequests-1.1.dist-info/RECORD
