Metadata-Version: 2.1
Name: ZeroXRequests
Version: 1.1
Summary: Requests for hackers
Home-page: https://github.com/rafax00/ZeroXRequests
Author: Rafax00
Author-email: 
License: MIT
Platform: UNKNOWN
Classifier: Programming Language :: Python :: 3
Classifier: License :: OSI Approved :: MIT License
Classifier: Operating System :: OS Independent
Requires-Python: >=3.6
Requires-Dist: requests
Requires-Dist: h2
